{
  "_id": "61151cbda4c377867481fdb0",
  "filename": "/Merino/003785MH4.jpg",
  "annotations": [
    {
      "id": "61151e4a28919b8bdc456484",
      "url": "https://gate.dataloop.ai/api/v1/annotations/61151e4a28919b8bdc456484",
      "creator": "or@dataloop.ai",
      "createdAt": "2021-08-12T13:12:42.975Z",
      "updatedBy": "or@dataloop.ai",
      "updatedAt": "2021-08-12T13:12:42.975Z",
      "metadata": {
        "system": {
          "automated": true
        }
      },
      "hash": "d87c0c52da5048f7f49b5798ff003f0273d2d4d9",
      "itemId": "61151cbda4c377867481fdb0",
      "item": "https://gate.dataloop.ai/api/v1/items/61151cbda4c377867481fdb0",
      "label": "Merino",
      "attributes": [],
      "dataset": "https://gate.dataloop.ai/api/v1/datasets/61151cb9e5759208912b4e8e",
      "datasetId": "61151cb9e5759208912b4e8e",
      "type": "class",
      "coordinates": []
    }
  ],
  "itemMetadata": {
    "system": {
      "originalname": "003785MH4.jpg",
      "size": 8188,
      "encoding": "7bit",
      "mimetype": "image/jpeg",
      "annotationStatus": [],
      "refs": [],
      "isBinary": true,
      "executionLogs": {
        "image-preprocess": {
          "default_module": {
            "on_create": {
              "61151cbd3570f95a0c6cc945": {
                "progress": 100,
                "status": "success"
              }
            }
          }
        }
      },
      "channels": 3,
      "exif": {},
      "height": 181,
      "thumbnailAnnotationsId": "61151cd851ab3788b81e158c",
      "thumbnailId": "61151cd685164979919348de",
      "width": 156
    }
  }
}