{
  "_id": "61151cbf107b76dfb8084fea",
  "filename": "/Marino/19.jpgMB7.jpg",
  "annotations": [
    {
      "id": "61151e2f8a305286362dca2a",
      "url": "https://gate.dataloop.ai/api/v1/annotations/61151e2f8a305286362dca2a",
      "creator": "or@dataloop.ai",
      "createdAt": "2021-08-12T13:12:15.381Z",
      "updatedBy": "or@dataloop.ai",
      "updatedAt": "2021-08-12T13:12:15.381Z",
      "metadata": {
        "system": {
          "automated": true
        }
      },
      "hash": "67a32f8c7cdc6501c52eeb76bdf179211c7e50c4",
      "itemId": "61151cbf107b76dfb8084fea",
      "item": "https://gate.dataloop.ai/api/v1/items/61151cbf107b76dfb8084fea",
      "label": "Marino",
      "attributes": [],
      "dataset": "https://gate.dataloop.ai/api/v1/datasets/61151cb9e5759208912b4e8e",
      "datasetId": "61151cb9e5759208912b4e8e",
      "type": "class",
      "coordinates": []
    }
  ],
  "itemMetadata": {
    "system": {
      "originalname": "19.jpgMB7.jpg",
      "size": 5885,
      "encoding": "7bit",
      "mimetype": "image/jpeg",
      "annotationStatus": [],
      "refs": [],
      "isBinary": true,
      "executionLogs": {
        "image-preprocess": {
          "default_module": {
            "on_create": {
              "61151cbff75a93078dcf1548": {
                "progress": 100,
                "status": "success"
              }
            }
          }
        }
      },
      "channels": 3,
      "exif": {},
      "height": 181,
      "thumbnailAnnotationsId": "61151ceb63195d5deaa70a2d",
      "thumbnailId": "61151ce8b8cf836e82c234e6",
      "width": 156
    }
  }
}